{"upload_date": "20210816", "extractor": "youtube", "height": 1440, "like_count": 235, "duration": 1228, "fulltitle": "793\uff1a\u7b2c\u4e00\u5c9b\u94fe\u5c31\u662f\u4e2d\u5171\u773c\u91cc\u7684\u4e00\u6761\u72d7\u94fe", "playlist_index": 61, "view_count": 3925, "playlist": "Spicy space - Videos", "average_rating": 4.8683128, "_filename": "20210816_98OqDq42dHQ.webm", "tags": ["\u4e2d\u7f8e\u8d38\u6613\u6218", "\u9999\u6e2f\u53cd\u9001\u4e2d", "\u4e2d\u56fd\u7ecf\u6d4e", "\u5b54\u5b50", "\u8001\u5b50", "\u5112\u5bb6\u601d\u60f3", "\u4e2d\u56fd\u6587\u5316", "\u4e2d\u56fd\u4e13\u5236", "\u7231\u56fd\u7ea2\u86c6", "\u5229\u7528\u7f8e\u56fd\u6cd5\u5f8b", "\u5077\u6e21", "\u5ddd\u666e", "\u7f8e\u56fd\u5927\u9009", "\u7279\u6717\u666e", "\u4eba\u6c11\u5e01\u8d2c\u503c", "\u65b0\u79fb\u6c11\u751f\u6d3b", "\u7f8e\u56fd\u79fb\u6c11\u751f", "\u4eba\u6c11\u5e01\u5d29\u76d8", "\u7f8e\u5143\u5347\u503c", "\u6c11\u4e3b\u4e0e\u81ea\u6cbb", "\u4e2d\u56fd\u4e92\u8054\u7f51", "\u9999\u6e2f\u8b66\u5bdf", "\u7ea2\u7c89", "\u6587\u9769\u7c89", "\u6c11\u65cf\u4e3b\u4e49\u7c89", "\u5171\u4ea7\u515a", "\u56fd\u6c11\u515a", "\u53f0\u6e7e\u6c11\u4e3b\u8fd0\u52a8", "\u4e2d\u56fd\u6c11\u4e3b\u8fd0\u52a8", "\u7f8e\u56fd\u5171\u548c\u515a", "\u7f8e\u56fd\u6c11\u4e3b\u515a", "2020\u5341\u5927\u9884\u8a00", "WTO", "\u4ea1\u56fd\u5974", "\u534e\u4e3a", "\u7f8e\u56fd\u5236\u88c1", "\u7f8e\u56fd\u5386\u53f2", "\u4e2d\u56fd\u5386\u53f2", "\u82f1\u56fd\u8131\u6b27", "\u7f8e\u56fd\u56fd\u4f1a", "\u7f8e\u56fd\u6cd5\u6848", "\u4eba\u6743\u7ec4\u7ec7", "\u601d\u60f3\u4e0e\u89e3\u653e", "\u72ec\u7acb\u601d\u8003", "\u8521\u82f1\u6587", "\u9a6c\u82f1\u4e5d", "\u4e60\u8fd1\u5e73", "\u4e2d\u56fd\u72d7\u7cae", "\u673a\u5668\u7c89", "\u5e74\u4ee3\u5411\u94b1\u770b", "\u6c6a\u7cbe\u536b", "\u56db\u5ddd\u666e\u901a\u8bdd", "\u6bdb\u6cfd\u4e1c", "\u65b0\u79fb\u6c11", "\u7f8e\u56fd\u79fb\u6c11", "\u4e2d\u56fd\u4eba\u6743", "\u65e5\u672c\u516c\u4e3b\u53f7\u90ae\u8f6e", "\u7f8e\u56fd\u5236\u88c1\u4e2d\u56fd", "\u4eba\u8138\u8bc6\u522b", "\u4e2d\u7f8e\u8131\u52fe", "\u4e2d\u56fd\u732a\u8089\u6da8\u4ef7", "\u6b66\u6c49", "\u6cd5\u6cbb\u4e0e\u4eba\u5236", "\u9999\u6e2f\u8f6e\u9677", "\u56fd\u5bb6\u5b89\u5168", "\u77e5\u8bc6\u4ea7\u6743", "\u534e\u4e3a\u76d7\u7a83", "\u7535\u89c6\u8ba4\u7f6a", "\u8001\u5d14\u8336\u9986", "\u79c0\u67285", "\u4e2d\u56fd\u7ea2\u86c6", "\u4e0a\u6d77\u5c01\u57ce", "\u4e2d\u56fd\u56fd\u6c11\u515a", "\u53f0\u6e7e\u6c11\u8fdb\u515a", "CCP", "\u534e\u4eba\u5728\u7f8e\u56fd", "\u73b0\u8c61\u5b66", "\u83cc\u6b66", "\u6b66\u88c5\u706d\u5171", "\u80a2\u89e3\u4e2d\u56fd", "\u72ec\u7acb\u5efa\u56fd"], "is_live": null, "id": "98OqDq42dHQ", "dislike_count": 8, "playlist_id": "UC7AyG3ABC8DPTDSe7jWSzHA", "abr": 129.475, "uploader_url": "http://www.youtube.com/channel/UC7AyG3ABC8DPTDSe7jWSzHA", "fps": 25, "stretched_ratio": null, "channel_url": "https://www.youtube.com/channel/UC7AyG3ABC8DPTDSe7jWSzHA", "thumbnail": "https://i.ytimg.com/vi/98OqDq42dHQ/maxresdefault.jpg", "webpage_url_basename": "98OqDq42dHQ", "acodec": "mp4a.40.2", "display_id": "98OqDq42dHQ", "description": "#\u53f0\u6e7e#\u7b2c\u4e00\u5c9b\u94fe#\u7f8e\u519b\n\u5492\u8bed\uff1a\u53d1\u51fa\u6765\u4e0d\u770b\u5c31\u70b9\u8e29\u7684\u4eba\u5176\u59bb\u5973\u88ab\u8f6e\u5978\u540e\u5168\u5bb6\u6b7b\u7edd\u3002\u6211\u4fe1\u795e\u7684\uff0c\u5492\u8bed\u8d85\u7075\u5e94\uff01\n\u52a0\u5bc6\u90ae\u7bb1\uff1awto518@protonmail.com\n\u81ea\u6211\u4ecb\u7ecd\n\u59d3\u540d\uff1a\u770b\u5de6\u4e0a\u65b9\n\u6027\u522b\uff1a\u5f53\u7136\u4e0d\u662f\u5973\u7684\n\u751f\u65e5\uff1a365\u5929\u91cc\u7684\u9f99\u65e5\u5929\n\u5c5e\u76f8\uff1a\u975e\u5e38\u8363\u5e78\u5c5e\u51e4\u51f0\n\u5b66\u5386\u3000\uff1a\u53cd\u6b63\u4e0d\u662f\u535a\u58eb\n\u804c\u4e1a\u3000\uff1a\u5143\u5e1d\u56fd\u4e0d\u5982\u5993\u5973\n\u559c\u6b22\u6ef4\u540d\u4eba\uff1a\u8001\u5b50\uff01\n\u6700\u559c\u6b22\u6ef4\u5b57\uff1a\u62c6\n\u6700\u559c\u6b22\u6ef4\u4e8b\uff1a\u6545\u5c45\u4e0a\uff0c\u81ea\u711a\uff01\n\u4e09\u89c2\u52a0\u4e00\u89c2\n\u4eba\u751f\u89c2\uff1a\u4e00\u76f4\u4ee5\u4e3a\uff0c\u5439\u725b\u662f\u4e00\u95e8\u5f88\u6709\u524d\u9014\u7684\u804c\u4e1a\uff01\n\u4ef7\u503c\u89c2\uff1a\u559c\u6b22\u770b\u8111\u5b50\u88ab\u95e8\u5939\u7740\u7684\u4eba\uff0c\u559c\u6b22\u770b\u5634\u5df4\u6bd4\u8138\u5927\u7684\u4eba\uff01\n\u4e16\u754c\u89c2\uff1a\u8001\u5b50\u662f\u601d\u60f3\u5bb6\uff0c\u4e0d\u4fe1\u4f60\u95ee\u8001\u5b50\uff01\n\u60b2\u559c\u89c2\uff1a\u4eba\u8fd9\u4e00\u751f\u80fd\u641e\u51fa\u4e9b\u4ec0\u4e48?\u4e0d\u5916\u4e4e\u6709\u4e8c\uff1a\u7537\u4eba\u625b\u7740\u5973\u4eba\u3001\u94b1\u548c\u540d\u88ab\u4e00\u6839\u7a3b\u8349\u538b\u6b7b\uff0c\u800c\u5973\u4eba\uff0c\u5f80\u98ce\u666f\u5904\u4e00\u7ad9\uff0c\u5373\u53ef\u7b11\u50b2\u6c5f\u6e56\uff01", "format": "271 - 2560x1440 (1440p)+140 - audio only (tiny)", "playlist_uploader": null, "uploader": "\u9ebb\u8fa3\u7a7a\u95f4", "format_id": "271+140", "uploader_id": "UC7AyG3ABC8DPTDSe7jWSzHA", "categories": ["News & Politics"], "playlist_title": "Spicy space - Videos", "thumbnails": [{"url": "https://i.ytimg.com/vi/98OqDq42dHQ/hqdefault.jpg?sqp=-oaymwEbCKgBEF5IVfKriqkDDggBFQAAiEIYAXABwAEG&rs=AOn4CLAJO4YT4uQ_afLO_-ZyULA3lttt1Q", "width": 168, "resolution": "168x94", "id": "0", "height": 94}, {"url": "https://i.ytimg.com/vi/98OqDq42dHQ/hqdefault.jpg?sqp=-oaymwEbCMQBEG5IVfKriqkDDggBFQAAiEIYAXABwAEG&rs=AOn4CLB73AUJKckOmSb2byAVy3gPG4k6tg", "width": 196, "resolution": "196x110", "id": "1", "height": 110}, {"url": "https://i.ytimg.com/vi/98OqDq42dHQ/hqdefault.jpg?sqp=-oaymwEcCPYBEIoBSFXyq4qpAw4IARUAAIhCGAFwAcABBg==&rs=AOn4CLDqFW4ADFQtaPagLdbXKX85T3oy0Q", "width": 246, "resolution": "246x138", "id": "2", "height": 138}, {"url": "https://i.ytimg.com/vi/98OqDq42dHQ/hqdefault.jpg?sqp=-oaymwEcCNACELwBSFXyq4qpAw4IARUAAIhCGAFwAcABBg==&rs=AOn4CLCjBxeOozjR5rLTnHLrmSnCFi2ZMw", "width": 336, "resolution": "336x188", "id": "3", "height": 188}, {"url": "https://i.ytimg.com/vi/98OqDq42dHQ/maxresdefault.jpg", "width": 1920, "resolution": "1920x1080", "id": "4", "height": 1080}], "channel_id": "UC7AyG3ABC8DPTDSe7jWSzHA", "extractor_key": "Youtube", "vcodec": "vp9", "title": "793\uff1a\u7b2c\u4e00\u5c9b\u94fe\u5c31\u662f\u4e2d\u5171\u773c\u91cc\u7684\u4e00\u6761\u72d7\u94fe", "vbr": 2883.471, "ext": "webm", "channel": "Spicy space", "webpage_url": "https://www.youtube.com/watch?v=98OqDq42dHQ", "formats": [{"asr": 48000, "format_note": "tiny", "protocol": "https", "format": "249 - audio only (tiny)", "tbr": 49.953, "height": null, "downloader_options": {"http_chunk_size": 10485760}, "format_id": "249", "quality": 0, "container": "webm_dash", "http_headers": {"Accept-Charset": "ISO-8859-1,utf-8;q=0.7,*;q=0.7", "Accept-Language": "en-us,en;q=0.5", "Accept-Encoding": "gzip, deflate", "Accept": "text/html,application/xhtml+xml,application/xml;q=0.9,*/*;q=0.8", "User-Agent": "Mozilla/5.0 (Windows NT 10.0; Win64; x64) AppleWebKit/537.36 (KHTML, like Gecko) Chrome/71.0.3578.126 Safari/537.36"}, "url": "https://r5---sn-vgqsknez.googlevideo.com/videoplayback?expire=1633505132&ei=DPtcYb_7CcG8uQLxqYmABA&ip=69.136.135.75&id=o-AGYAEcH-AvOV28Vk6YabN_wwsyX_N2rHAoK6-bEHE29J&itag=249&source=youtube&requiressl=yes&mh=0M&mm=31%2C26&mn=sn-vgqsknez%2Csn-p5qs7n76&ms=au%2Conr&mv=m&mvi=5&pl=19&initcwndbps=1890000&vprv=1&mime=audio%2Fwebm&ns=cb_W2nbbIV-nuoo4CqlbvPIG&gir=yes&clen=7667072&dur=1227.881&lmt=1629165205073265&mt=1633483256&fvip=5&keepalive=yes&fexp=24001373%2C24007246&c=WEB&txp=5411222&n=mNcNuO0MQMuueuHW&sparams=expire%2Cei%2Cip%2Cid%2Citag%2Csource%2Crequiressl%2Cvprv%2Cmime%2Cns%2Cgir%2Cclen%2Cdur%2Clmt&sig=AOq0QJ8wRQIhAP8i7R4h1F6T874frAKlT-QShQJPJ7w50B_yTdGJnCAaAiBXug4OuJrObKBvJ3vyI-O34TrECrtiCOkT0GdNN1XTZg%3D%3D&lsparams=mh%2Cmm%2Cmn%2Cms%2Cmv%2Cmvi%2Cpl%2Cinitcwndbps&lsig=AG3C_xAwRAIgB15CJADXFxPPDbJ4XnseUAUVmMag16XzeRvl9GCCqOYCIHM7d8jQhHjJs8-2ze5qDOUa-vJitGWE9Y9cU6mI82MA", "vcodec": "none", "abr": 49.953, "width": null, "ext": "webm", "filesize": 7667072, "fps": null, "acodec": "opus"}, {"asr": 48000, "format_note": "tiny", "protocol": "https", "format": "250 - audio only (tiny)", "tbr": 56.473, "height": null, "downloader_options": {"http_chunk_size": 10485760}, "format_id": "250", "quality": 0, "container": "webm_dash", "http_headers": {"Accept-Charset": "ISO-8859-1,utf-8;q=0.7,*;q=0.7", "Accept-Language": "en-us,en;q=0.5", "Accept-Encoding": "gzip, deflate", "Accept": "text/html,application/xhtml+xml,application/xml;q=0.9,*/*;q=0.8", "User-Agent": "Mozilla/5.0 (Windows NT 10.0; Win64; x64) AppleWebKit/537.36 (KHTML, like Gecko) Chrome/71.0.3578.126 Safari/537.36"}, "url": "https://r5---sn-vgqsknez.googlevideo.com/videoplayback?expire=1633505132&ei=DPtcYb_7CcG8uQLxqYmABA&ip=69.136.135.75&id=o-AGYAEcH-AvOV28Vk6YabN_wwsyX_N2rHAoK6-bEHE29J&itag=250&source=youtube&requiressl=yes&mh=0M&mm=31%2C26&mn=sn-vgqsknez%2Csn-p5qs7n76&ms=au%2Conr&mv=m&mvi=5&pl=19&initcwndbps=1890000&vprv=1&mime=audio%2Fwebm&ns=cb_W2nbbIV-nuoo4CqlbvPIG&gir=yes&clen=8667833&dur=1227.881&lmt=1629165166927357&mt=1633483256&fvip=5&keepalive=yes&fexp=24001373%2C24007246&c=WEB&txp=5411222&n=mNcNuO0MQMuueuHW&sparams=expire%2Cei%2Cip%2Cid%2Citag%2Csource%2Crequiressl%2Cvprv%2Cmime%2Cns%2Cgir%2Cclen%2Cdur%2Clmt&sig=AOq0QJ8wRQIgQS3SAveBXZMZXNZySAxcSe7X8xDi4fBBV-BVb0QsqtgCIQDQtKhMY1tsJwRTSjBSFR5V0p1y_3H0ByKrbeZMkTVNnA%3D%3D&lsparams=mh%2Cmm%2Cmn%2Cms%2Cmv%2Cmvi%2Cpl%2Cinitcwndbps&lsig=AG3C_xAwRAIgB15CJADXFxPPDbJ4XnseUAUVmMag16XzeRvl9GCCqOYCIHM7d8jQhHjJs8-2ze5qDOUa-vJitGWE9Y9cU6mI82MA", "vcodec": "none", "abr": 56.473, "width": null, "ext": "webm", "filesize": 8667833, "fps": null, "acodec": "opus"}, {"asr": 48000, "format_note": "tiny", "protocol": "https", "format": "251 - audio only (tiny)", "tbr": 102.772, "height": null, "downloader_options": {"http_chunk_size": 10485760}, "format_id": "251", "quality": 0, "container": "webm_dash", "http_headers": {"Accept-Charset": "ISO-8859-1,utf-8;q=0.7,*;q=0.7", "Accept-Language": "en-us,en;q=0.5", "Accept-Encoding": "gzip, deflate", "Accept": "text/html,application/xhtml+xml,application/xml;q=0.9,*/*;q=0.8", "User-Agent": "Mozilla/5.0 (Windows NT 10.0; Win64; x64) AppleWebKit/537.36 (KHTML, like Gecko) Chrome/71.0.3578.126 Safari/537.36"}, "url": "https://r5---sn-vgqsknez.googlevideo.com/videoplayback?expire=1633505132&ei=DPtcYb_7CcG8uQLxqYmABA&ip=69.136.135.75&id=o-AGYAEcH-AvOV28Vk6YabN_wwsyX_N2rHAoK6-bEHE29J&itag=251&source=youtube&requiressl=yes&mh=0M&mm=31%2C26&mn=sn-vgqsknez%2Csn-p5qs7n76&ms=au%2Conr&mv=m&mvi=5&pl=19&initcwndbps=1890000&vprv=1&mime=audio%2Fwebm&ns=cb_W2nbbIV-nuoo4CqlbvPIG&gir=yes&clen=15774123&dur=1227.881&lmt=1629165170334078&mt=1633483256&fvip=5&keepalive=yes&fexp=24001373%2C24007246&c=WEB&txp=5411222&n=mNcNuO0MQMuueuHW&sparams=expire%2Cei%2Cip%2Cid%2Citag%2Csource%2Crequiressl%2Cvprv%2Cmime%2Cns%2Cgir%2Cclen%2Cdur%2Clmt&sig=AOq0QJ8wRQIhAOuKZ44mzlooGJcXpHZxlYFBaVv-eIuQnYyby-w-SVtTAiB-_BmtNjtF6mYdOLgUkGQuHpERl0Y41iisovFmCUUKfw%3D%3D&lsparams=mh%2Cmm%2Cmn%2Cms%2Cmv%2Cmvi%2Cpl%2Cinitcwndbps&lsig=AG3C_xAwRAIgB15CJADXFxPPDbJ4XnseUAUVmMag16XzeRvl9GCCqOYCIHM7d8jQhHjJs8-2ze5qDOUa-vJitGWE9Y9cU6mI82MA", "vcodec": "none", "abr": 102.772, "width": null, "ext": "webm", "filesize": 15774123, "fps": null, "acodec": "opus"}, {"asr": 44100, "format_note": "tiny", "protocol": "https", "format": "140 - audio only (tiny)", "tbr": 129.475, "height": null, "downloader_options": {"http_chunk_size": 10485760}, "format_id": "140", "quality": 0, "container": "m4a_dash", "http_headers": {"Accept-Charset": "ISO-8859-1,utf-8;q=0.7,*;q=0.7", "Accept-Language": "en-us,en;q=0.5", "Accept-Encoding": "gzip, deflate", "Accept": "text/html,application/xhtml+xml,application/xml;q=0.9,*/*;q=0.8", "User-Agent": "Mozilla/5.0 (Windows NT 10.0; Win64; x64) AppleWebKit/537.36 (KHTML, like Gecko) Chrome/71.0.3578.126 Safari/537.36"}, "url": "https://r5---sn-vgqsknez.googlevideo.com/videoplayback?expire=1633505132&ei=DPtcYb_7CcG8uQLxqYmABA&ip=69.136.135.75&id=o-AGYAEcH-AvOV28Vk6YabN_wwsyX_N2rHAoK6-bEHE29J&itag=140&source=youtube&requiressl=yes&mh=0M&mm=31%2C26&mn=sn-vgqsknez%2Csn-p5qs7n76&ms=au%2Conr&mv=m&mvi=5&pl=19&initcwndbps=1890000&vprv=1&mime=audio%2Fmp4&ns=cb_W2nbbIV-nuoo4CqlbvPIG&gir=yes&clen=19873517&dur=1227.940&lmt=1629360519154051&mt=1633483256&fvip=5&keepalive=yes&fexp=24001373%2C24007246&c=WEB&txp=5431432&n=mNcNuO0MQMuueuHW&sparams=expire%2Cei%2Cip%2Cid%2Citag%2Csource%2Crequiressl%2Cvprv%2Cmime%2Cns%2Cgir%2Cclen%2Cdur%2Clmt&sig=AOq0QJ8wRAIgQItkJJ0J7Bdhglst_ndvaoDO1t91wehNtkf8302nqU8CIBqD_WY6o_Ek9UTMF9-zZ2c8bEPJ9lXZ2PBt5qki9chZ&lsparams=mh%2Cmm%2Cmn%2Cms%2Cmv%2Cmvi%2Cpl%2Cinitcwndbps&lsig=AG3C_xAwRAIgB15CJADXFxPPDbJ4XnseUAUVmMag16XzeRvl9GCCqOYCIHM7d8jQhHjJs8-2ze5qDOUa-vJitGWE9Y9cU6mI82MA", "vcodec": "none", "abr": 129.475, "width": null, "ext": "m4a", "filesize": 19873517, "fps": null, "acodec": "mp4a.40.2"}, {"asr": null, "format_note": "144p", "protocol": "https", "format": "160 - 256x144 (144p)", "tbr": 38.499, "height": 144, "downloader_options": {"http_chunk_size": 10485760}, "format_id": "160", "quality": 0, "container": "mp4_dash", "vbr": 38.499, "url": "https://r5---sn-vgqsknez.googlevideo.com/videoplayback?expire=1633505132&ei=DPtcYb_7CcG8uQLxqYmABA&ip=69.136.135.75&id=o-AGYAEcH-AvOV28Vk6YabN_wwsyX_N2rHAoK6-bEHE29J&itag=160&aitags=133%2C134%2C135%2C136%2C137%2C160%2C242%2C243%2C244%2C247%2C248%2C271%2C278%2C394%2C395%2C396%2C397%2C398%2C399%2C400&source=youtube&requiressl=yes&mh=0M&mm=31%2C26&mn=sn-vgqsknez%2Csn-p5qs7n76&ms=au%2Conr&mv=m&mvi=5&pl=19&initcwndbps=1890000&vprv=1&mime=video%2Fmp4&ns=cb_W2nbbIV-nuoo4CqlbvPIG&gir=yes&clen=5908660&dur=1227.800&lmt=1629360554780731&mt=1633483256&fvip=5&keepalive=yes&fexp=24001373%2C24007246&c=WEB&txp=5432432&n=mNcNuO0MQMuueuHW&sparams=expire%2Cei%2Cip%2Cid%2Caitags%2Csource%2Crequiressl%2Cvprv%2Cmime%2Cns%2Cgir%2Cclen%2Cdur%2Clmt&sig=AOq0QJ8wRQIhALWpLpgmxIFd7_DKT_c8uFxzVs0ljeWItyHxkRaiw48TAiBihYt1QE3szwwW0wFdf5bCgVTuDQI7Wnyma_dh2UpDSg%3D%3D&lsparams=mh%2Cmm%2Cmn%2Cms%2Cmv%2Cmvi%2Cpl%2Cinitcwndbps&lsig=AG3C_xAwRAIgB15CJADXFxPPDbJ4XnseUAUVmMag16XzeRvl9GCCqOYCIHM7d8jQhHjJs8-2ze5qDOUa-vJitGWE9Y9cU6mI82MA", "vcodec": "avc1.4d400c", "http_headers": {"Accept-Charset": "ISO-8859-1,utf-8;q=0.7,*;q=0.7", "Accept-Language": "en-us,en;q=0.5", "Accept-Encoding": "gzip, deflate", "Accept": "text/html,application/xhtml+xml,application/xml;q=0.9,*/*;q=0.8", "User-Agent": "Mozilla/5.0 (Windows NT 10.0; Win64; x64) AppleWebKit/537.36 (KHTML, like Gecko) Chrome/71.0.3578.126 Safari/537.36"}, "width": 256, "ext": "mp4", "filesize": 5908660, "fps": 25, "acodec": "none"}, {"asr": null, "format_note": "144p", "protocol": "https", "format": "278 - 256x144 (144p)", "tbr": 81.669, "height": 144, "downloader_options": {"http_chunk_size": 10485760}, "format_id": "278", "quality": 0, "container": "webm_dash", "vbr": 81.669, "url": "https://r5---sn-vgqsknez.googlevideo.com/videoplayback?expire=1633505132&ei=DPtcYb_7CcG8uQLxqYmABA&ip=69.136.135.75&id=o-AGYAEcH-AvOV28Vk6YabN_wwsyX_N2rHAoK6-bEHE29J&itag=278&aitags=133%2C134%2C135%2C136%2C137%2C160%2C242%2C243%2C244%2C247%2C248%2C271%2C278%2C394%2C395%2C396%2C397%2C398%2C399%2C400&source=youtube&requiressl=yes&mh=0M&mm=31%2C26&mn=sn-vgqsknez%2Csn-p5qs7n76&ms=au%2Conr&mv=m&mvi=5&pl=19&initcwndbps=1890000&vprv=1&mime=video%2Fwebm&ns=cb_W2nbbIV-nuoo4CqlbvPIG&gir=yes&clen=12534292&dur=1227.800&lmt=1629360962279743&mt=1633483256&fvip=5&keepalive=yes&fexp=24001373%2C24007246&c=WEB&txp=5432432&n=mNcNuO0MQMuueuHW&sparams=expire%2Cei%2Cip%2Cid%2Caitags%2Csource%2Crequiressl%2Cvprv%2Cmime%2Cns%2Cgir%2Cclen%2Cdur%2Clmt&sig=AOq0QJ8wRQIhAIsFrmQZiAhb-Gz9JAp0aMm9X7aFAtGwBR904aa3lhx_AiBBNvbQmaqCFSY99HAI1HbKX6gW5CpvhRSjkctBsp6ZDw%3D%3D&lsparams=mh%2Cmm%2Cmn%2Cms%2Cmv%2Cmvi%2Cpl%2Cinitcwndbps&lsig=AG3C_xAwRAIgB15CJADXFxPPDbJ4XnseUAUVmMag16XzeRvl9GCCqOYCIHM7d8jQhHjJs8-2ze5qDOUa-vJitGWE9Y9cU6mI82MA", "vcodec": "vp9", "http_headers": {"Accept-Charset": "ISO-8859-1,utf-8;q=0.7,*;q=0.7", "Accept-Language": "en-us,en;q=0.5", "Accept-Encoding": "gzip, deflate", "Accept": "text/html,application/xhtml+xml,application/xml;q=0.9,*/*;q=0.8", "User-Agent": "Mozilla/5.0 (Windows NT 10.0; Win64; x64) AppleWebKit/537.36 (KHTML, like Gecko) Chrome/71.0.3578.126 Safari/537.36"}, "width": 256, "ext": "webm", "filesize": 12534292, "fps": 25, "acodec": "none"}, {"asr": null, "format_note": "144p", "protocol": "https", "format": "394 - 256x144 (144p)", "tbr": 81.765, "height": 144, "downloader_options": {"http_chunk_size": 10485760}, "format_id": "394", "quality": 0, "container": "mp4_dash", "vbr": 81.765, "url": "https://r5---sn-vgqsknez.googlevideo.com/videoplayback?expire=1633505132&ei=DPtcYb_7CcG8uQLxqYmABA&ip=69.136.135.75&id=o-AGYAEcH-AvOV28Vk6YabN_wwsyX_N2rHAoK6-bEHE29J&itag=394&aitags=133%2C134%2C135%2C136%2C137%2C160%2C242%2C243%2C244%2C247%2C248%2C271%2C278%2C394%2C395%2C396%2C397%2C398%2C399%2C400&source=youtube&requiressl=yes&mh=0M&mm=31%2C26&mn=sn-vgqsknez%2Csn-p5qs7n76&ms=au%2Conr&mv=m&mvi=5&pl=19&initcwndbps=1890000&vprv=1&mime=video%2Fmp4&ns=cb_W2nbbIV-nuoo4CqlbvPIG&gir=yes&clen=12548891&dur=1227.800&lmt=1629727652443933&mt=1633483256&fvip=5&keepalive=yes&fexp=24001373%2C24007246&c=WEB&txp=5436434&n=mNcNuO0MQMuueuHW&sparams=expire%2Cei%2Cip%2Cid%2Caitags%2Csource%2Crequiressl%2Cvprv%2Cmime%2Cns%2Cgir%2Cclen%2Cdur%2Clmt&sig=AOq0QJ8wRAIgdxF0tcm_4yCqngq9FurxyOsek2g_q-TggP7To09uQMUCIGvjg95fy_NY2yqVZvNET4_bO5HN_OlFVQDGtZz9nLXB&lsparams=mh%2Cmm%2Cmn%2Cms%2Cmv%2Cmvi%2Cpl%2Cinitcwndbps&lsig=AG3C_xAwRAIgB15CJADXFxPPDbJ4XnseUAUVmMag16XzeRvl9GCCqOYCIHM7d8jQhHjJs8-2ze5qDOUa-vJitGWE9Y9cU6mI82MA", "vcodec": "av01.0.00M.08", "http_headers": {"Accept-Charset": "ISO-8859-1,utf-8;q=0.7,*;q=0.7", "Accept-Language": "en-us,en;q=0.5", "Accept-Encoding": "gzip, deflate", "Accept": "text/html,application/xhtml+xml,application/xml;q=0.9,*/*;q=0.8", "User-Agent": "Mozilla/5.0 (Windows NT 10.0; Win64; x64) AppleWebKit/537.36 (KHTML, like Gecko) Chrome/71.0.3578.126 Safari/537.36"}, "width": 256, "ext": "mp4", "filesize": 12548891, "fps": 25, "acodec": "none"}, {"asr": null, "format_note": "240p", "protocol": "https", "format": "133 - 426x240 (240p)", "tbr": 74.532, "height": 240, "downloader_options": {"http_chunk_size": 10485760}, "format_id": "133", "quality": 1, "container": "mp4_dash", "vbr": 74.532, "url": "https://r5---sn-vgqsknez.googlevideo.com/videoplayback?expire=1633505132&ei=DPtcYb_7CcG8uQLxqYmABA&ip=69.136.135.75&id=o-AGYAEcH-AvOV28Vk6YabN_wwsyX_N2rHAoK6-bEHE29J&itag=133&aitags=133%2C134%2C135%2C136%2C137%2C160%2C242%2C243%2C244%2C247%2C248%2C271%2C278%2C394%2C395%2C396%2C397%2C398%2C399%2C400&source=youtube&requiressl=yes&mh=0M&mm=31%2C26&mn=sn-vgqsknez%2Csn-p5qs7n76&ms=au%2Conr&mv=m&mvi=5&pl=19&initcwndbps=1890000&vprv=1&mime=video%2Fmp4&ns=cb_W2nbbIV-nuoo4CqlbvPIG&gir=yes&clen=11438862&dur=1227.800&lmt=1629360554780768&mt=1633483256&fvip=5&keepalive=yes&fexp=24001373%2C24007246&c=WEB&txp=5432432&n=mNcNuO0MQMuueuHW&sparams=expire%2Cei%2Cip%2Cid%2Caitags%2Csource%2Crequiressl%2Cvprv%2Cmime%2Cns%2Cgir%2Cclen%2Cdur%2Clmt&sig=AOq0QJ8wRAIgchGDcGtgIzEATt4awAf16n5oEdPFJMBqHjO6F5j4NYkCIHegDgDRUoVUi1qwNkbX7BzPOVxOXIsFtZxvKZfC5OlZ&lsparams=mh%2Cmm%2Cmn%2Cms%2Cmv%2Cmvi%2Cpl%2Cinitcwndbps&lsig=AG3C_xAwRAIgB15CJADXFxPPDbJ4XnseUAUVmMag16XzeRvl9GCCqOYCIHM7d8jQhHjJs8-2ze5qDOUa-vJitGWE9Y9cU6mI82MA", "vcodec": "avc1.4d4015", "http_headers": {"Accept-Charset": "ISO-8859-1,utf-8;q=0.7,*;q=0.7", "Accept-Language": "en-us,en;q=0.5", "Accept-Encoding": "gzip, deflate", "Accept": "text/html,application/xhtml+xml,application/xml;q=0.9,*/*;q=0.8", "User-Agent": "Mozilla/5.0 (Windows NT 10.0; Win64; x64) AppleWebKit/537.36 (KHTML, like Gecko) Chrome/71.0.3578.126 Safari/537.36"}, "width": 426, "ext": "mp4", "filesize": 11438862, "fps": 25, "acodec": "none"}, {"asr": null, "format_note": "240p", "protocol": "https", "format": "242 - 426x240 (240p)", "tbr": 105.51, "height": 240, "downloader_options": {"http_chunk_size": 10485760}, "format_id": "242", "quality": 1, "container": "webm_dash", "vbr": 105.51, "url": "https://r5---sn-vgqsknez.googlevideo.com/videoplayback?expire=1633505132&ei=DPtcYb_7CcG8uQLxqYmABA&ip=69.136.135.75&id=o-AGYAEcH-AvOV28Vk6YabN_wwsyX_N2rHAoK6-bEHE29J&itag=242&aitags=133%2C134%2C135%2C136%2C137%2C160%2C242%2C243%2C244%2C247%2C248%2C271%2C278%2C394%2C395%2C396%2C397%2C398%2C399%2C400&source=youtube&requiressl=yes&mh=0M&mm=31%2C26&mn=sn-vgqsknez%2Csn-p5qs7n76&ms=au%2Conr&mv=m&mvi=5&pl=19&initcwndbps=1890000&vprv=1&mime=video%2Fwebm&ns=cb_W2nbbIV-nuoo4CqlbvPIG&gir=yes&clen=16193292&dur=1227.800&lmt=1629360962211023&mt=1633483256&fvip=5&keepalive=yes&fexp=24001373%2C24007246&c=WEB&txp=5432432&n=mNcNuO0MQMuueuHW&sparams=expire%2Cei%2Cip%2Cid%2Caitags%2Csource%2Crequiressl%2Cvprv%2Cmime%2Cns%2Cgir%2Cclen%2Cdur%2Clmt&sig=AOq0QJ8wRgIhAOFSGV4W3j-5Zz4ojUS_0Q-8or2PqA5CZmKo1ulpC7W1AiEAtjCfUygrI2fUGug_NYmbKYjMAphFt4XStKEvyywLKuQ%3D&lsparams=mh%2Cmm%2Cmn%2Cms%2Cmv%2Cmvi%2Cpl%2Cinitcwndbps&lsig=AG3C_xAwRAIgB15CJADXFxPPDbJ4XnseUAUVmMag16XzeRvl9GCCqOYCIHM7d8jQhHjJs8-2ze5qDOUa-vJitGWE9Y9cU6mI82MA", "vcodec": "vp9", "http_headers": {"Accept-Charset": "ISO-8859-1,utf-8;q=0.7,*;q=0.7", "Accept-Language": "en-us,en;q=0.5", "Accept-Encoding": "gzip, deflate", "Accept": "text/html,application/xhtml+xml,application/xml;q=0.9,*/*;q=0.8", "User-Agent": "Mozilla/5.0 (Windows NT 10.0; Win64; x64) AppleWebKit/537.36 (KHTML, like Gecko) Chrome/71.0.3578.126 Safari/537.36"}, "width": 426, "ext": "webm", "filesize": 16193292, "fps": 25, "acodec": "none"}, {"asr": null, "format_note": "240p", "protocol": "https", "format": "395 - 426x240 (240p)", "tbr": 119.628, "height": 240, "downloader_options": {"http_chunk_size": 10485760}, "format_id": "395", "quality": 1, "container": "mp4_dash", "vbr": 119.628, "url": "https://r5---sn-vgqsknez.googlevideo.com/videoplayback?expire=1633505132&ei=DPtcYb_7CcG8uQLxqYmABA&ip=69.136.135.75&id=o-AGYAEcH-AvOV28Vk6YabN_wwsyX_N2rHAoK6-bEHE29J&itag=395&aitags=133%2C134%2C135%2C136%2C137%2C160%2C242%2C243%2C244%2C247%2C248%2C271%2C278%2C394%2C395%2C396%2C397%2C398%2C399%2C400&source=youtube&requiressl=yes&mh=0M&mm=31%2C26&mn=sn-vgqsknez%2Csn-p5qs7n76&ms=au%2Conr&mv=m&mvi=5&pl=19&initcwndbps=1890000&vprv=1&mime=video%2Fmp4&ns=cb_W2nbbIV-nuoo4CqlbvPIG&gir=yes&clen=18359982&dur=1227.800&lmt=1629727644792600&mt=1633483256&fvip=5&keepalive=yes&fexp=24001373%2C24007246&c=WEB&txp=5436434&n=mNcNuO0MQMuueuHW&sparams=expire%2Cei%2Cip%2Cid%2Caitags%2Csource%2Crequiressl%2Cvprv%2Cmime%2Cns%2Cgir%2Cclen%2Cdur%2Clmt&sig=AOq0QJ8wRQIgf5KuXzrrEHyPXZEQhB3B9YLlwiZfB5BZCTOEHYO9iZECIQCquLmEtYfdiuvyngdlkT-sRgTsLedQ0TAjqa8W7yfdIA%3D%3D&lsparams=mh%2Cmm%2Cmn%2Cms%2Cmv%2Cmvi%2Cpl%2Cinitcwndbps&lsig=AG3C_xAwRAIgB15CJADXFxPPDbJ4XnseUAUVmMag16XzeRvl9GCCqOYCIHM7d8jQhHjJs8-2ze5qDOUa-vJitGWE9Y9cU6mI82MA", "vcodec": "av01.0.00M.08", "http_headers": {"Accept-Charset": "ISO-8859-1,utf-8;q=0.7,*;q=0.7", "Accept-Language": "en-us,en;q=0.5", "Accept-Encoding": "gzip, deflate", "Accept": "text/html,application/xhtml+xml,application/xml;q=0.9,*/*;q=0.8", "User-Agent": "Mozilla/5.0 (Windows NT 10.0; Win64; x64) AppleWebKit/537.36 (KHTML, like Gecko) Chrome/71.0.3578.126 Safari/537.36"}, "width": 426, "ext": "mp4", "filesize": 18359982, "fps": 25, "acodec": "none"}, {"asr": null, "format_note": "360p", "protocol": "https", "format": "134 - 640x360 (360p)", "tbr": 139.335, "height": 360, "downloader_options": {"http_chunk_size": 10485760}, "format_id": "134", "quality": 2, "container": "mp4_dash", "vbr": 139.335, "url": "https://r5---sn-vgqsknez.googlevideo.com/videoplayback?expire=1633505132&ei=DPtcYb_7CcG8uQLxqYmABA&ip=69.136.135.75&id=o-AGYAEcH-AvOV28Vk6YabN_wwsyX_N2rHAoK6-bEHE29J&itag=134&aitags=133%2C134%2C135%2C136%2C137%2C160%2C242%2C243%2C244%2C247%2C248%2C271%2C278%2C394%2C395%2C396%2C397%2C398%2C399%2C400&source=youtube&requiressl=yes&mh=0M&mm=31%2C26&mn=sn-vgqsknez%2Csn-p5qs7n76&ms=au%2Conr&mv=m&mvi=5&pl=19&initcwndbps=1890000&vprv=1&mime=video%2Fmp4&ns=cb_W2nbbIV-nuoo4CqlbvPIG&gir=yes&clen=21384498&dur=1227.800&lmt=1629360554782667&mt=1633483256&fvip=5&keepalive=yes&fexp=24001373%2C24007246&c=WEB&txp=5432432&n=mNcNuO0MQMuueuHW&sparams=expire%2Cei%2Cip%2Cid%2Caitags%2Csource%2Crequiressl%2Cvprv%2Cmime%2Cns%2Cgir%2Cclen%2Cdur%2Clmt&sig=AOq0QJ8wRAIgJc4FKlv2aast-DhoAM6zEIO7cBkW_IN9Pwz2k5hhhq0CIDTALa30lN5gam1IawmKCvBUCyrRO8uhCqI2UqVhUje2&lsparams=mh%2Cmm%2Cmn%2Cms%2Cmv%2Cmvi%2Cpl%2Cinitcwndbps&lsig=AG3C_xAwRAIgB15CJADXFxPPDbJ4XnseUAUVmMag16XzeRvl9GCCqOYCIHM7d8jQhHjJs8-2ze5qDOUa-vJitGWE9Y9cU6mI82MA", "vcodec": "avc1.4d401e", "http_headers": {"Accept-Charset": "ISO-8859-1,utf-8;q=0.7,*;q=0.7", "Accept-Language": "en-us,en;q=0.5", "Accept-Encoding": "gzip, deflate", "Accept": "text/html,application/xhtml+xml,application/xml;q=0.9,*/*;q=0.8", "User-Agent": "Mozilla/5.0 (Windows NT 10.0; Win64; x64) AppleWebKit/537.36 (KHTML, like Gecko) Chrome/71.0.3578.126 Safari/537.36"}, "width": 640, "ext": "mp4", "filesize": 21384498, "fps": 25, "acodec": "none"}, {"asr": null, "format_note": "360p", "protocol": "https", "format": "396 - 640x360 (360p)", "tbr": 204.38, "height": 360, "downloader_options": {"http_chunk_size": 10485760}, "format_id": "396", "quality": 2, "container": "mp4_dash", "vbr": 204.38, "url": "https://r5---sn-vgqsknez.googlevideo.com/videoplayback?expire=1633505132&ei=DPtcYb_7CcG8uQLxqYmABA&ip=69.136.135.75&id=o-AGYAEcH-AvOV28Vk6YabN_wwsyX_N2rHAoK6-bEHE29J&itag=396&aitags=133%2C134%2C135%2C136%2C137%2C160%2C242%2C243%2C244%2C247%2C248%2C271%2C278%2C394%2C395%2C396%2C397%2C398%2C399%2C400&source=youtube&requiressl=yes&mh=0M&mm=31%2C26&mn=sn-vgqsknez%2Csn-p5qs7n76&ms=au%2Conr&mv=m&mvi=5&pl=19&initcwndbps=1890000&vprv=1&mime=video%2Fmp4&ns=cb_W2nbbIV-nuoo4CqlbvPIG&gir=yes&clen=31367355&dur=1227.800&lmt=1629727664471133&mt=1633483256&fvip=5&keepalive=yes&fexp=24001373%2C24007246&c=WEB&txp=5436434&n=mNcNuO0MQMuueuHW&sparams=expire%2Cei%2Cip%2Cid%2Caitags%2Csource%2Crequiressl%2Cvprv%2Cmime%2Cns%2Cgir%2Cclen%2Cdur%2Clmt&sig=AOq0QJ8wRQIhAJshTAzosi_uwXpPPU1JYzKelcn_oinQ54egE5KvVxIsAiADYgTlysGMzdX2fvxQOx9KylQxZ_qksQzRZi-J9qoYeg%3D%3D&lsparams=mh%2Cmm%2Cmn%2Cms%2Cmv%2Cmvi%2Cpl%2Cinitcwndbps&lsig=AG3C_xAwRAIgB15CJADXFxPPDbJ4XnseUAUVmMag16XzeRvl9GCCqOYCIHM7d8jQhHjJs8-2ze5qDOUa-vJitGWE9Y9cU6mI82MA", "vcodec": "av01.0.01M.08", "http_headers": {"Accept-Charset": "ISO-8859-1,utf-8;q=0.7,*;q=0.7", "Accept-Language": "en-us,en;q=0.5", "Accept-Encoding": "gzip, deflate", "Accept": "text/html,application/xhtml+xml,application/xml;q=0.9,*/*;q=0.8", "User-Agent": "Mozilla/5.0 (Windows NT 10.0; Win64; x64) AppleWebKit/537.36 (KHTML, like Gecko) Chrome/71.0.3578.126 Safari/537.36"}, "width": 640, "ext": "mp4", "filesize": 31367355, "fps": 25, "acodec": "none"}, {"asr": null, "format_note": "360p", "protocol": "https", "format": "243 - 640x360 (360p)", "tbr": 212.131, "height": 360, "downloader_options": {"http_chunk_size": 10485760}, "format_id": "243", "quality": 2, "container": "webm_dash", "vbr": 212.131, "url": "https://r5---sn-vgqsknez.googlevideo.com/videoplayback?expire=1633505132&ei=DPtcYb_7CcG8uQLxqYmABA&ip=69.136.135.75&id=o-AGYAEcH-AvOV28Vk6YabN_wwsyX_N2rHAoK6-bEHE29J&itag=243&aitags=133%2C134%2C135%2C136%2C137%2C160%2C242%2C243%2C244%2C247%2C248%2C271%2C278%2C394%2C395%2C396%2C397%2C398%2C399%2C400&source=youtube&requiressl=yes&mh=0M&mm=31%2C26&mn=sn-vgqsknez%2Csn-p5qs7n76&ms=au%2Conr&mv=m&mvi=5&pl=19&initcwndbps=1890000&vprv=1&mime=video%2Fwebm&ns=cb_W2nbbIV-nuoo4CqlbvPIG&gir=yes&clen=32556880&dur=1227.800&lmt=1629360962213214&mt=1633483256&fvip=5&keepalive=yes&fexp=24001373%2C24007246&c=WEB&txp=5432432&n=mNcNuO0MQMuueuHW&sparams=expire%2Cei%2Cip%2Cid%2Caitags%2Csource%2Crequiressl%2Cvprv%2Cmime%2Cns%2Cgir%2Cclen%2Cdur%2Clmt&sig=AOq0QJ8wRQIhALTAJCZGjJz3NIlAnIlUHhse-CDoMQHA_m9LKDaWf2BFAiApAqPUGY7u7VQIlb7vP4iBEXzBJ4lWpdlrrz9vePQbug%3D%3D&lsparams=mh%2Cmm%2Cmn%2Cms%2Cmv%2Cmvi%2Cpl%2Cinitcwndbps&lsig=AG3C_xAwRAIgB15CJADXFxPPDbJ4XnseUAUVmMag16XzeRvl9GCCqOYCIHM7d8jQhHjJs8-2ze5qDOUa-vJitGWE9Y9cU6mI82MA", "vcodec": "vp9", "http_headers": {"Accept-Charset": "ISO-8859-1,utf-8;q=0.7,*;q=0.7", "Accept-Language": "en-us,en;q=0.5", "Accept-Encoding": "gzip, deflate", "Accept": "text/html,application/xhtml+xml,application/xml;q=0.9,*/*;q=0.8", "User-Agent": "Mozilla/5.0 (Windows NT 10.0; Win64; x64) AppleWebKit/537.36 (KHTML, like Gecko) Chrome/71.0.3578.126 Safari/537.36"}, "width": 640, "ext": "webm", "filesize": 32556880, "fps": 25, "acodec": "none"}, {"asr": null, "format_note": "480p", "protocol": "https", "format": "135 - 854x480 (480p)", "tbr": 216.223, "height": 480, "downloader_options": {"http_chunk_size": 10485760}, "format_id": "135", "quality": 3, "container": "mp4_dash", "vbr": 216.223, "url": "https://r5---sn-vgqsknez.googlevideo.com/videoplayback?expire=1633505132&ei=DPtcYb_7CcG8uQLxqYmABA&ip=69.136.135.75&id=o-AGYAEcH-AvOV28Vk6YabN_wwsyX_N2rHAoK6-bEHE29J&itag=135&aitags=133%2C134%2C135%2C136%2C137%2C160%2C242%2C243%2C244%2C247%2C248%2C271%2C278%2C394%2C395%2C396%2C397%2C398%2C399%2C400&source=youtube&requiressl=yes&mh=0M&mm=31%2C26&mn=sn-vgqsknez%2Csn-p5qs7n76&ms=au%2Conr&mv=m&mvi=5&pl=19&initcwndbps=1890000&vprv=1&mime=video%2Fmp4&ns=cb_W2nbbIV-nuoo4CqlbvPIG&gir=yes&clen=33184900&dur=1227.800&lmt=1629360554782797&mt=1633483256&fvip=5&keepalive=yes&fexp=24001373%2C24007246&c=WEB&txp=5432432&n=mNcNuO0MQMuueuHW&sparams=expire%2Cei%2Cip%2Cid%2Caitags%2Csource%2Crequiressl%2Cvprv%2Cmime%2Cns%2Cgir%2Cclen%2Cdur%2Clmt&sig=AOq0QJ8wRAIgJ5PdGm1UYX6RAIdynJZBj2Jg-dFtuwrGdpV5HMTkSbcCIFt-2jaZ03nRAk2e2ppU_N60w_KdhDrbcObwhfrB6RCt&lsparams=mh%2Cmm%2Cmn%2Cms%2Cmv%2Cmvi%2Cpl%2Cinitcwndbps&lsig=AG3C_xAwRAIgB15CJADXFxPPDbJ4XnseUAUVmMag16XzeRvl9GCCqOYCIHM7d8jQhHjJs8-2ze5qDOUa-vJitGWE9Y9cU6mI82MA", "vcodec": "avc1.4d401e", "http_headers": {"Accept-Charset": "ISO-8859-1,utf-8;q=0.7,*;q=0.7", "Accept-Language": "en-us,en;q=0.5", "Accept-Encoding": "gzip, deflate", "Accept": "text/html,application/xhtml+xml,application/xml;q=0.9,*/*;q=0.8", "User-Agent": "Mozilla/5.0 (Windows NT 10.0; Win64; x64) AppleWebKit/537.36 (KHTML, like Gecko) Chrome/71.0.3578.126 Safari/537.36"}, "width": 854, "ext": "mp4", "filesize": 33184900, "fps": 25, "acodec": "none"}, {"asr": null, "format_note": "480p", "protocol": "https", "format": "397 - 854x480 (480p)", "tbr": 291.832, "height": 480, "downloader_options": {"http_chunk_size": 10485760}, "format_id": "397", "quality": 3, "container": "mp4_dash", "vbr": 291.832, "url": "https://r5---sn-vgqsknez.googlevideo.com/videoplayback?expire=1633505132&ei=DPtcYb_7CcG8uQLxqYmABA&ip=69.136.135.75&id=o-AGYAEcH-AvOV28Vk6YabN_wwsyX_N2rHAoK6-bEHE29J&itag=397&aitags=133%2C134%2C135%2C136%2C137%2C160%2C242%2C243%2C244%2C247%2C248%2C271%2C278%2C394%2C395%2C396%2C397%2C398%2C399%2C400&source=youtube&requiressl=yes&mh=0M&mm=31%2C26&mn=sn-vgqsknez%2Csn-p5qs7n76&ms=au%2Conr&mv=m&mvi=5&pl=19&initcwndbps=1890000&vprv=1&mime=video%2Fmp4&ns=cb_W2nbbIV-nuoo4CqlbvPIG&gir=yes&clen=44789036&dur=1227.800&lmt=1629727653150166&mt=1633483256&fvip=5&keepalive=yes&fexp=24001373%2C24007246&c=WEB&txp=5436434&n=mNcNuO0MQMuueuHW&sparams=expire%2Cei%2Cip%2Cid%2Caitags%2Csource%2Crequiressl%2Cvprv%2Cmime%2Cns%2Cgir%2Cclen%2Cdur%2Clmt&sig=AOq0QJ8wRgIhAJvHGFvZB6FohHwSQRyz2rvC3WhLKdfnVmyAHGoKsndZAiEAkxkB5bnEhFpJPvCIp7VCph0YXVDyNvXnIKPE6pYdYjY%3D&lsparams=mh%2Cmm%2Cmn%2Cms%2Cmv%2Cmvi%2Cpl%2Cinitcwndbps&lsig=AG3C_xAwRAIgB15CJADXFxPPDbJ4XnseUAUVmMag16XzeRvl9GCCqOYCIHM7d8jQhHjJs8-2ze5qDOUa-vJitGWE9Y9cU6mI82MA", "vcodec": "av01.0.04M.08", "http_headers": {"Accept-Charset": "ISO-8859-1,utf-8;q=0.7,*;q=0.7", "Accept-Language": "en-us,en;q=0.5", "Accept-Encoding": "gzip, deflate", "Accept": "text/html,application/xhtml+xml,application/xml;q=0.9,*/*;q=0.8", "User-Agent": "Mozilla/5.0 (Windows NT 10.0; Win64; x64) AppleWebKit/537.36 (KHTML, like Gecko) Chrome/71.0.3578.126 Safari/537.36"}, "width": 854, "ext": "mp4", "filesize": 44789036, "fps": 25, "acodec": "none"}, {"asr": null, "format_note": "480p", "protocol": "https", "format": "244 - 854x480 (480p)", "tbr": 339.856, "height": 480, "downloader_options": {"http_chunk_size": 10485760}, "format_id": "244", "quality": 3, "container": "webm_dash", "vbr": 339.856, "url": "https://r5---sn-vgqsknez.googlevideo.com/videoplayback?expire=1633505132&ei=DPtcYb_7CcG8uQLxqYmABA&ip=69.136.135.75&id=o-AGYAEcH-AvOV28Vk6YabN_wwsyX_N2rHAoK6-bEHE29J&itag=244&aitags=133%2C134%2C135%2C136%2C137%2C160%2C242%2C243%2C244%2C247%2C248%2C271%2C278%2C394%2C395%2C396%2C397%2C398%2C399%2C400&source=youtube&requiressl=yes&mh=0M&mm=31%2C26&mn=sn-vgqsknez%2Csn-p5qs7n76&ms=au%2Conr&mv=m&mvi=5&pl=19&initcwndbps=1890000&vprv=1&mime=video%2Fwebm&ns=cb_W2nbbIV-nuoo4CqlbvPIG&gir=yes&clen=52159468&dur=1227.800&lmt=1629360962213077&mt=1633483256&fvip=5&keepalive=yes&fexp=24001373%2C24007246&c=WEB&txp=5432432&n=mNcNuO0MQMuueuHW&sparams=expire%2Cei%2Cip%2Cid%2Caitags%2Csource%2Crequiressl%2Cvprv%2Cmime%2Cns%2Cgir%2Cclen%2Cdur%2Clmt&sig=AOq0QJ8wRQIgbCD0B9UDq17qhh9qZVuHwoMvBoCVEj8txpwvuE90McYCIQC9o_HRMl0R2HtltXeGSRVX8kYxLmpvsgWT_3VljTFLlg%3D%3D&lsparams=mh%2Cmm%2Cmn%2Cms%2Cmv%2Cmvi%2Cpl%2Cinitcwndbps&lsig=AG3C_xAwRAIgB15CJADXFxPPDbJ4XnseUAUVmMag16XzeRvl9GCCqOYCIHM7d8jQhHjJs8-2ze5qDOUa-vJitGWE9Y9cU6mI82MA", "vcodec": "vp9", "http_headers": {"Accept-Charset": "ISO-8859-1,utf-8;q=0.7,*;q=0.7", "Accept-Language": "en-us,en;q=0.5", "Accept-Encoding": "gzip, deflate", "Accept": "text/html,application/xhtml+xml,application/xml;q=0.9,*/*;q=0.8", "User-Agent": "Mozilla/5.0 (Windows NT 10.0; Win64; x64) AppleWebKit/537.36 (KHTML, like Gecko) Chrome/71.0.3578.126 Safari/537.36"}, "width": 854, "ext": "webm", "filesize": 52159468, "fps": 25, "acodec": "none"}, {"asr": null, "format_note": "720p", "protocol": "https", "format": "136 - 1280x720 (720p)", "tbr": 335.83, "height": 720, "downloader_options": {"http_chunk_size": 10485760}, "format_id": "136", "quality": 4, "container": "mp4_dash", "vbr": 335.83, "url": "https://r5---sn-vgqsknez.googlevideo.com/videoplayback?expire=1633505132&ei=DPtcYb_7CcG8uQLxqYmABA&ip=69.136.135.75&id=o-AGYAEcH-AvOV28Vk6YabN_wwsyX_N2rHAoK6-bEHE29J&itag=136&aitags=133%2C134%2C135%2C136%2C137%2C160%2C242%2C243%2C244%2C247%2C248%2C271%2C278%2C394%2C395%2C396%2C397%2C398%2C399%2C400&source=youtube&requiressl=yes&mh=0M&mm=31%2C26&mn=sn-vgqsknez%2Csn-p5qs7n76&ms=au%2Conr&mv=m&mvi=5&pl=19&initcwndbps=1890000&vprv=1&mime=video%2Fmp4&ns=cb_W2nbbIV-nuoo4CqlbvPIG&gir=yes&clen=51541563&dur=1227.800&lmt=1629360554779210&mt=1633483256&fvip=5&keepalive=yes&fexp=24001373%2C24007246&c=WEB&txp=5432432&n=mNcNuO0MQMuueuHW&sparams=expire%2Cei%2Cip%2Cid%2Caitags%2Csource%2Crequiressl%2Cvprv%2Cmime%2Cns%2Cgir%2Cclen%2Cdur%2Clmt&sig=AOq0QJ8wRQIhAMbEKv_ts2xTjmDizCl2STDfFqLK2VEHR7kA024_YCz1AiB5pV6zw-FSdvR2dksXYyQ4okzsmyEyiLALveIq7tQ-LA%3D%3D&lsparams=mh%2Cmm%2Cmn%2Cms%2Cmv%2Cmvi%2Cpl%2Cinitcwndbps&lsig=AG3C_xAwRAIgB15CJADXFxPPDbJ4XnseUAUVmMag16XzeRvl9GCCqOYCIHM7d8jQhHjJs8-2ze5qDOUa-vJitGWE9Y9cU6mI82MA", "vcodec": "avc1.4d401f", "http_headers": {"Accept-Charset": "ISO-8859-1,utf-8;q=0.7,*;q=0.7", "Accept-Language": "en-us,en;q=0.5", "Accept-Encoding": "gzip, deflate", "Accept": "text/html,application/xhtml+xml,application/xml;q=0.9,*/*;q=0.8", "User-Agent": "Mozilla/5.0 (Windows NT 10.0; Win64; x64) AppleWebKit/537.36 (KHTML, like Gecko) Chrome/71.0.3578.126 Safari/537.36"}, "width": 1280, "ext": "mp4", "filesize": 51541563, "fps": 25, "acodec": "none"}, {"asr": null, "format_note": "720p", "protocol": "https", "format": "398 - 1280x720 (720p)", "tbr": 513.459, "height": 720, "downloader_options": {"http_chunk_size": 10485760}, "format_id": "398", "quality": 4, "container": "mp4_dash", "vbr": 513.459, "url": "https://r5---sn-vgqsknez.googlevideo.com/videoplayback?expire=1633505132&ei=DPtcYb_7CcG8uQLxqYmABA&ip=69.136.135.75&id=o-AGYAEcH-AvOV28Vk6YabN_wwsyX_N2rHAoK6-bEHE29J&itag=398&aitags=133%2C134%2C135%2C136%2C137%2C160%2C242%2C243%2C244%2C247%2C248%2C271%2C278%2C394%2C395%2C396%2C397%2C398%2C399%2C400&source=youtube&requiressl=yes&mh=0M&mm=31%2C26&mn=sn-vgqsknez%2Csn-p5qs7n76&ms=au%2Conr&mv=m&mvi=5&pl=19&initcwndbps=1890000&vprv=1&mime=video%2Fmp4&ns=cb_W2nbbIV-nuoo4CqlbvPIG&gir=yes&clen=78803184&dur=1227.800&lmt=1629727715628765&mt=1633483256&fvip=5&keepalive=yes&fexp=24001373%2C24007246&c=WEB&txp=5436434&n=mNcNuO0MQMuueuHW&sparams=expire%2Cei%2Cip%2Cid%2Caitags%2Csource%2Crequiressl%2Cvprv%2Cmime%2Cns%2Cgir%2Cclen%2Cdur%2Clmt&sig=AOq0QJ8wRAIhAP5N9ofRQ9PuprcgskvlZ-CRkEYW5KSpVs2xtSMmzQ-GAh9Mt7zGAvnNd0S6P2-3C8QOXpm-RFVsbMYbcdJSEp_y&lsparams=mh%2Cmm%2Cmn%2Cms%2Cmv%2Cmvi%2Cpl%2Cinitcwndbps&lsig=AG3C_xAwRAIgB15CJADXFxPPDbJ4XnseUAUVmMag16XzeRvl9GCCqOYCIHM7d8jQhHjJs8-2ze5qDOUa-vJitGWE9Y9cU6mI82MA", "vcodec": "av01.0.05M.08", "http_headers": {"Accept-Charset": "ISO-8859-1,utf-8;q=0.7,*;q=0.7", "Accept-Language": "en-us,en;q=0.5", "Accept-Encoding": "gzip, deflate", "Accept": "text/html,application/xhtml+xml,application/xml;q=0.9,*/*;q=0.8", "User-Agent": "Mozilla/5.0 (Windows NT 10.0; Win64; x64) AppleWebKit/537.36 (KHTML, like Gecko) Chrome/71.0.3578.126 Safari/537.36"}, "width": 1280, "ext": "mp4", "filesize": 78803184, "fps": 25, "acodec": "none"}, {"asr": null, "format_note": "720p", "protocol": "https", "format": "247 - 1280x720 (720p)", "tbr": 643.055, "height": 720, "downloader_options": {"http_chunk_size": 10485760}, "format_id": "247", "quality": 4, "container": "webm_dash", "vbr": 643.055, "url": "https://r5---sn-vgqsknez.googlevideo.com/videoplayback?expire=1633505132&ei=DPtcYb_7CcG8uQLxqYmABA&ip=69.136.135.75&id=o-AGYAEcH-AvOV28Vk6YabN_wwsyX_N2rHAoK6-bEHE29J&itag=247&aitags=133%2C134%2C135%2C136%2C137%2C160%2C242%2C243%2C244%2C247%2C248%2C271%2C278%2C394%2C395%2C396%2C397%2C398%2C399%2C400&source=youtube&requiressl=yes&mh=0M&mm=31%2C26&mn=sn-vgqsknez%2Csn-p5qs7n76&ms=au%2Conr&mv=m&mvi=5&pl=19&initcwndbps=1890000&vprv=1&mime=video%2Fwebm&ns=cb_W2nbbIV-nuoo4CqlbvPIG&gir=yes&clen=98692894&dur=1227.800&lmt=1629360962213842&mt=1633483256&fvip=5&keepalive=yes&fexp=24001373%2C24007246&c=WEB&txp=5432432&n=mNcNuO0MQMuueuHW&sparams=expire%2Cei%2Cip%2Cid%2Caitags%2Csource%2Crequiressl%2Cvprv%2Cmime%2Cns%2Cgir%2Cclen%2Cdur%2Clmt&sig=AOq0QJ8wRgIhAMlSDcD4o1tR_qhsVGO2hcpkJU-LaRyiqXW9Tm8dAEMiAiEAlaCLNsVWBmRiXnJZYrSub7mJWia-nJ_XuBI5lNH_OnE%3D&lsparams=mh%2Cmm%2Cmn%2Cms%2Cmv%2Cmvi%2Cpl%2Cinitcwndbps&lsig=AG3C_xAwRAIgB15CJADXFxPPDbJ4XnseUAUVmMag16XzeRvl9GCCqOYCIHM7d8jQhHjJs8-2ze5qDOUa-vJitGWE9Y9cU6mI82MA", "vcodec": "vp9", "http_headers": {"Accept-Charset": "ISO-8859-1,utf-8;q=0.7,*;q=0.7", "Accept-Language": "en-us,en;q=0.5", "Accept-Encoding": "gzip, deflate", "Accept": "text/html,application/xhtml+xml,application/xml;q=0.9,*/*;q=0.8", "User-Agent": "Mozilla/5.0 (Windows NT 10.0; Win64; x64) AppleWebKit/537.36 (KHTML, like Gecko) Chrome/71.0.3578.126 Safari/537.36"}, "width": 1280, "ext": "webm", "filesize": 98692894, "fps": 25, "acodec": "none"}, {"asr": null, "format_note": "1080p", "protocol": "https", "format": "248 - 1920x1080 (1080p)", "tbr": 1192.583, "height": 1080, "downloader_options": {"http_chunk_size": 10485760}, "format_id": "248", "quality": 5, "container": "webm_dash", "vbr": 1192.583, "url": "https://r5---sn-vgqsknez.googlevideo.com/videoplayback?expire=1633505132&ei=DPtcYb_7CcG8uQLxqYmABA&ip=69.136.135.75&id=o-AGYAEcH-AvOV28Vk6YabN_wwsyX_N2rHAoK6-bEHE29J&itag=248&aitags=133%2C134%2C135%2C136%2C137%2C160%2C242%2C243%2C244%2C247%2C248%2C271%2C278%2C394%2C395%2C396%2C397%2C398%2C399%2C400&source=youtube&requiressl=yes&mh=0M&mm=31%2C26&mn=sn-vgqsknez%2Csn-p5qs7n76&ms=au%2Conr&mv=m&mvi=5&pl=19&initcwndbps=1890000&vprv=1&mime=video%2Fwebm&ns=cb_W2nbbIV-nuoo4CqlbvPIG&gir=yes&clen=183031778&dur=1227.800&lmt=1629360799238615&mt=1633483256&fvip=5&keepalive=yes&fexp=24001373%2C24007246&c=WEB&txp=5432432&n=mNcNuO0MQMuueuHW&sparams=expire%2Cei%2Cip%2Cid%2Caitags%2Csource%2Crequiressl%2Cvprv%2Cmime%2Cns%2Cgir%2Cclen%2Cdur%2Clmt&sig=AOq0QJ8wRQIgPjpLSuIlZ3WlcGWBG4VD-5HdRzbvJHFTFEs7jKmwrvECIQDB5UsScxFui3U3Z83ojguMUWGKiI__JphmHTJ6PfGdJw%3D%3D&lsparams=mh%2Cmm%2Cmn%2Cms%2Cmv%2Cmvi%2Cpl%2Cinitcwndbps&lsig=AG3C_xAwRAIgB15CJADXFxPPDbJ4XnseUAUVmMag16XzeRvl9GCCqOYCIHM7d8jQhHjJs8-2ze5qDOUa-vJitGWE9Y9cU6mI82MA", "vcodec": "vp9", "http_headers": {"Accept-Charset": "ISO-8859-1,utf-8;q=0.7,*;q=0.7", "Accept-Language": "en-us,en;q=0.5", "Accept-Encoding": "gzip, deflate", "Accept": "text/html,application/xhtml+xml,application/xml;q=0.9,*/*;q=0.8", "User-Agent": "Mozilla/5.0 (Windows NT 10.0; Win64; x64) AppleWebKit/537.36 (KHTML, like Gecko) Chrome/71.0.3578.126 Safari/537.36"}, "width": 1920, "ext": "webm", "filesize": 183031778, "fps": 25, "acodec": "none"}, {"asr": null, "format_note": "1080p", "protocol": "https", "format": "399 - 1920x1080 (1080p)", "tbr": 1209.721, "height": 1080, "downloader_options": {"http_chunk_size": 10485760}, "format_id": "399", "quality": 5, "container": "mp4_dash", "vbr": 1209.721, "url": "https://r5---sn-vgqsknez.googlevideo.com/videoplayback?expire=1633505132&ei=DPtcYb_7CcG8uQLxqYmABA&ip=69.136.135.75&id=o-AGYAEcH-AvOV28Vk6YabN_wwsyX_N2rHAoK6-bEHE29J&itag=399&aitags=133%2C134%2C135%2C136%2C137%2C160%2C242%2C243%2C244%2C247%2C248%2C271%2C278%2C394%2C395%2C396%2C397%2C398%2C399%2C400&source=youtube&requiressl=yes&mh=0M&mm=31%2C26&mn=sn-vgqsknez%2Csn-p5qs7n76&ms=au%2Conr&mv=m&mvi=5&pl=19&initcwndbps=1890000&vprv=1&mime=video%2Fmp4&ns=cb_W2nbbIV-nuoo4CqlbvPIG&gir=yes&clen=185661990&dur=1227.800&lmt=1629727685924951&mt=1633483256&fvip=5&keepalive=yes&fexp=24001373%2C24007246&c=WEB&txp=5436434&n=mNcNuO0MQMuueuHW&sparams=expire%2Cei%2Cip%2Cid%2Caitags%2Csource%2Crequiressl%2Cvprv%2Cmime%2Cns%2Cgir%2Cclen%2Cdur%2Clmt&sig=AOq0QJ8wRQIgcCPHRsADgA3wWNFLsUOjBo-3gVqGrYQKURjSBrQQu_gCIQDVh9VxAoUk-eBL_tJjOx25xMXPuoCRliV17MoRz4irrw%3D%3D&lsparams=mh%2Cmm%2Cmn%2Cms%2Cmv%2Cmvi%2Cpl%2Cinitcwndbps&lsig=AG3C_xAwRAIgB15CJADXFxPPDbJ4XnseUAUVmMag16XzeRvl9GCCqOYCIHM7d8jQhHjJs8-2ze5qDOUa-vJitGWE9Y9cU6mI82MA", "vcodec": "av01.0.08M.08", "http_headers": {"Accept-Charset": "ISO-8859-1,utf-8;q=0.7,*;q=0.7", "Accept-Language": "en-us,en;q=0.5", "Accept-Encoding": "gzip, deflate", "Accept": "text/html,application/xhtml+xml,application/xml;q=0.9,*/*;q=0.8", "User-Agent": "Mozilla/5.0 (Windows NT 10.0; Win64; x64) AppleWebKit/537.36 (KHTML, like Gecko) Chrome/71.0.3578.126 Safari/537.36"}, "width": 1920, "ext": "mp4", "filesize": 185661990, "fps": 25, "acodec": "none"}, {"asr": null, "format_note": "1080p", "protocol": "https", "format": "137 - 1920x1080 (1080p)", "tbr": 1227.185, "height": 1080, "downloader_options": {"http_chunk_size": 10485760}, "format_id": "137", "quality": 5, "container": "mp4_dash", "vbr": 1227.185, "url": "https://r5---sn-vgqsknez.googlevideo.com/videoplayback?expire=1633505132&ei=DPtcYb_7CcG8uQLxqYmABA&ip=69.136.135.75&id=o-AGYAEcH-AvOV28Vk6YabN_wwsyX_N2rHAoK6-bEHE29J&itag=137&aitags=133%2C134%2C135%2C136%2C137%2C160%2C242%2C243%2C244%2C247%2C248%2C271%2C278%2C394%2C395%2C396%2C397%2C398%2C399%2C400&source=youtube&requiressl=yes&mh=0M&mm=31%2C26&mn=sn-vgqsknez%2Csn-p5qs7n76&ms=au%2Conr&mv=m&mvi=5&pl=19&initcwndbps=1890000&vprv=1&mime=video%2Fmp4&ns=cb_W2nbbIV-nuoo4CqlbvPIG&gir=yes&clen=188342333&dur=1227.800&lmt=1629360560387956&mt=1633483256&fvip=5&keepalive=yes&fexp=24001373%2C24007246&c=WEB&txp=5432432&n=mNcNuO0MQMuueuHW&sparams=expire%2Cei%2Cip%2Cid%2Caitags%2Csource%2Crequiressl%2Cvprv%2Cmime%2Cns%2Cgir%2Cclen%2Cdur%2Clmt&sig=AOq0QJ8wRAIgaUktjcCyexHbewKzZikQR5caVLEIXLR4L-ShyevmQXUCIHsIemwfvgRzvx0uH9aofqVrSzsWDBCZoFINjdhEG-xi&lsparams=mh%2Cmm%2Cmn%2Cms%2Cmv%2Cmvi%2Cpl%2Cinitcwndbps&lsig=AG3C_xAwRAIgB15CJADXFxPPDbJ4XnseUAUVmMag16XzeRvl9GCCqOYCIHM7d8jQhHjJs8-2ze5qDOUa-vJitGWE9Y9cU6mI82MA", "vcodec": "avc1.640028", "http_headers": {"Accept-Charset": "ISO-8859-1,utf-8;q=0.7,*;q=0.7", "Accept-Language": "en-us,en;q=0.5", "Accept-Encoding": "gzip, deflate", "Accept": "text/html,application/xhtml+xml,application/xml;q=0.9,*/*;q=0.8", "User-Agent": "Mozilla/5.0 (Windows NT 10.0; Win64; x64) AppleWebKit/537.36 (KHTML, like Gecko) Chrome/71.0.3578.126 Safari/537.36"}, "width": 1920, "ext": "mp4", "filesize": 188342333, "fps": 25, "acodec": "none"}, {"asr": null, "format_note": "1440p", "protocol": "https", "format": "400 - 2560x1440 (1440p)", "tbr": 2117.191, "height": 1440, "downloader_options": {"http_chunk_size": 10485760}, "format_id": "400", "quality": 6, "container": "mp4_dash", "vbr": 2117.191, "url": "https://r5---sn-vgqsknez.googlevideo.com/videoplayback?expire=1633505132&ei=DPtcYb_7CcG8uQLxqYmABA&ip=69.136.135.75&id=o-AGYAEcH-AvOV28Vk6YabN_wwsyX_N2rHAoK6-bEHE29J&itag=400&aitags=133%2C134%2C135%2C136%2C137%2C160%2C242%2C243%2C244%2C247%2C248%2C271%2C278%2C394%2C395%2C396%2C397%2C398%2C399%2C400&source=youtube&requiressl=yes&mh=0M&mm=31%2C26&mn=sn-vgqsknez%2Csn-p5qs7n76&ms=au%2Conr&mv=m&mvi=5&pl=19&initcwndbps=1890000&vprv=1&mime=video%2Fmp4&ns=cb_W2nbbIV-nuoo4CqlbvPIG&gir=yes&clen=324935908&dur=1227.800&lmt=1629727725334916&mt=1633483256&fvip=5&keepalive=yes&fexp=24001373%2C24007246&c=WEB&txp=5436434&n=mNcNuO0MQMuueuHW&sparams=expire%2Cei%2Cip%2Cid%2Caitags%2Csource%2Crequiressl%2Cvprv%2Cmime%2Cns%2Cgir%2Cclen%2Cdur%2Clmt&sig=AOq0QJ8wRQIgC43VERKnTXiGdOw3Ni2VQV57gBWlaAFRFfkEiXKfIXwCIQD8iQzveUGXR7JWyeHav3-TiyCr7v0uwAlKscKLUy1LXQ%3D%3D&lsparams=mh%2Cmm%2Cmn%2Cms%2Cmv%2Cmvi%2Cpl%2Cinitcwndbps&lsig=AG3C_xAwRAIgB15CJADXFxPPDbJ4XnseUAUVmMag16XzeRvl9GCCqOYCIHM7d8jQhHjJs8-2ze5qDOUa-vJitGWE9Y9cU6mI82MA", "vcodec": "av01.0.12M.08", "http_headers": {"Accept-Charset": "ISO-8859-1,utf-8;q=0.7,*;q=0.7", "Accept-Language": "en-us,en;q=0.5", "Accept-Encoding": "gzip, deflate", "Accept": "text/html,application/xhtml+xml,application/xml;q=0.9,*/*;q=0.8", "User-Agent": "Mozilla/5.0 (Windows NT 10.0; Win64; x64) AppleWebKit/537.36 (KHTML, like Gecko) Chrome/71.0.3578.126 Safari/537.36"}, "width": 2560, "ext": "mp4", "filesize": 324935908, "fps": 25, "acodec": "none"}, {"asr": null, "format_note": "1440p", "protocol": "https", "format": "271 - 2560x1440 (1440p)", "tbr": 2883.471, "height": 1440, "downloader_options": {"http_chunk_size": 10485760}, "format_id": "271", "quality": 6, "container": "webm_dash", "vbr": 2883.471, "url": "https://r5---sn-vgqsknez.googlevideo.com/videoplayback?expire=1633505132&ei=DPtcYb_7CcG8uQLxqYmABA&ip=69.136.135.75&id=o-AGYAEcH-AvOV28Vk6YabN_wwsyX_N2rHAoK6-bEHE29J&itag=271&aitags=133%2C134%2C135%2C136%2C137%2C160%2C242%2C243%2C244%2C247%2C248%2C271%2C278%2C394%2C395%2C396%2C397%2C398%2C399%2C400&source=youtube&requiressl=yes&mh=0M&mm=31%2C26&mn=sn-vgqsknez%2Csn-p5qs7n76&ms=au%2Conr&mv=m&mvi=5&pl=19&initcwndbps=1890000&vprv=1&mime=video%2Fwebm&ns=cb_W2nbbIV-nuoo4CqlbvPIG&gir=yes&clen=442540836&dur=1227.800&lmt=1629361010384349&mt=1633483256&fvip=5&keepalive=yes&fexp=24001373%2C24007246&c=WEB&txp=5432432&n=mNcNuO0MQMuueuHW&sparams=expire%2Cei%2Cip%2Cid%2Caitags%2Csource%2Crequiressl%2Cvprv%2Cmime%2Cns%2Cgir%2Cclen%2Cdur%2Clmt&sig=AOq0QJ8wRgIhAKu5ayx_NG-d14WbQEX6aP4ntlE0d0e7ijJHZox00jLdAiEAm7OHiuodgLwNie9uo1Qs1JyzB_Vgh3aHLRtirDEcfvM%3D&lsparams=mh%2Cmm%2Cmn%2Cms%2Cmv%2Cmvi%2Cpl%2Cinitcwndbps&lsig=AG3C_xAwRAIgB15CJADXFxPPDbJ4XnseUAUVmMag16XzeRvl9GCCqOYCIHM7d8jQhHjJs8-2ze5qDOUa-vJitGWE9Y9cU6mI82MA", "vcodec": "vp9", "http_headers": {"Accept-Charset": "ISO-8859-1,utf-8;q=0.7,*;q=0.7", "Accept-Language": "en-us,en;q=0.5", "Accept-Encoding": "gzip, deflate", "Accept": "text/html,application/xhtml+xml,application/xml;q=0.9,*/*;q=0.8", "User-Agent": "Mozilla/5.0 (Windows NT 10.0; Win64; x64) AppleWebKit/537.36 (KHTML, like Gecko) Chrome/71.0.3578.126 Safari/537.36"}, "width": 2560, "ext": "webm", "filesize": 442540836, "fps": 25, "acodec": "none"}, {"asr": 44100, "format_note": "360p", "protocol": "https", "format": "18 - 640x360 (360p)", "tbr": 398.357, "height": 360, "format_id": "18", "quality": 2, "http_headers": {"Accept-Charset": "ISO-8859-1,utf-8;q=0.7,*;q=0.7", "Accept-Language": "en-us,en;q=0.5", "Accept-Encoding": "gzip, deflate", "Accept": "text/html,application/xhtml+xml,application/xml;q=0.9,*/*;q=0.8", "User-Agent": "Mozilla/5.0 (Windows NT 10.0; Win64; x64) AppleWebKit/537.36 (KHTML, like Gecko) Chrome/71.0.3578.126 Safari/537.36"}, "url": "https://r5---sn-vgqsknez.googlevideo.com/videoplayback?expire=1633505132&ei=DPtcYb_7CcG8uQLxqYmABA&ip=69.136.135.75&id=o-AGYAEcH-AvOV28Vk6YabN_wwsyX_N2rHAoK6-bEHE29J&itag=18&source=youtube&requiressl=yes&mh=0M&mm=31%2C26&mn=sn-vgqsknez%2Csn-p5qs7n76&ms=au%2Conr&mv=m&mvi=5&pl=19&initcwndbps=1890000&vprv=1&mime=video%2Fmp4&ns=SBTGDh9K4bFQoNBcQEqiIvIG&gir=yes&clen=61144956&ratebypass=yes&dur=1227.940&lmt=1629179492062237&mt=1633483256&fvip=5&fexp=24001373%2C24007246&c=WEB&txp=5430434&n=7oa8d0XoVpTg6G4z&sparams=expire%2Cei%2Cip%2Cid%2Citag%2Csource%2Crequiressl%2Cvprv%2Cmime%2Cns%2Cgir%2Cclen%2Cratebypass%2Cdur%2Clmt&sig=AOq0QJ8wRgIhAKtHcmyUaiOAwJA4eRrjHm2-DlnukzjVrBWMG3hVLNjnAiEAx_uNWolFbZqTYvM0Y_zeURg4ddhha7Qsvo0oPkyiVCI%3D&lsparams=mh%2Cmm%2Cmn%2Cms%2Cmv%2Cmvi%2Cpl%2Cinitcwndbps&lsig=AG3C_xAwRAIgB15CJADXFxPPDbJ4XnseUAUVmMag16XzeRvl9GCCqOYCIHM7d8jQhHjJs8-2ze5qDOUa-vJitGWE9Y9cU6mI82MA", "vcodec": "avc1.42001E", "width": 640, "ext": "mp4", "filesize": 61144956, "fps": 25, "acodec": "mp4a.40.2"}, {"asr": 44100, "format_note": "720p", "protocol": "https", "format": "22 - 1280x720 (720p)", "tbr": 464.969, "height": 720, "format_id": "22", "quality": 4, "http_headers": {"Accept-Charset": "ISO-8859-1,utf-8;q=0.7,*;q=0.7", "Accept-Language": "en-us,en;q=0.5", "Accept-Encoding": "gzip, deflate", "Accept": "text/html,application/xhtml+xml,application/xml;q=0.9,*/*;q=0.8", "User-Agent": "Mozilla/5.0 (Windows NT 10.0; Win64; x64) AppleWebKit/537.36 (KHTML, like Gecko) Chrome/71.0.3578.126 Safari/537.36"}, "url": "https://r5---sn-vgqsknez.googlevideo.com/videoplayback?expire=1633505132&ei=DPtcYb_7CcG8uQLxqYmABA&ip=69.136.135.75&id=o-AGYAEcH-AvOV28Vk6YabN_wwsyX_N2rHAoK6-bEHE29J&itag=22&source=youtube&requiressl=yes&mh=0M&mm=31%2C26&mn=sn-vgqsknez%2Csn-p5qs7n76&ms=au%2Conr&mv=m&mvi=5&pl=19&initcwndbps=1890000&vprv=1&mime=video%2Fmp4&ns=SBTGDh9K4bFQoNBcQEqiIvIG&cnr=14&ratebypass=yes&dur=1227.940&lmt=1629360578499745&mt=1633483256&fvip=5&fexp=24001373%2C24007246&c=WEB&txp=5432432&n=7oa8d0XoVpTg6G4z&sparams=expire%2Cei%2Cip%2Cid%2Citag%2Csource%2Crequiressl%2Cvprv%2Cmime%2Cns%2Ccnr%2Cratebypass%2Cdur%2Clmt&sig=AOq0QJ8wRgIhAJj3So-3J7F6ozN_oJ7GU_qDym_eJ1tucEo01UzLsUiDAiEA1p8M6rQxvBa9RsQ1tJNuv0O_obF7GPJEgCmmCUqqw2U%3D&lsparams=mh%2Cmm%2Cmn%2Cms%2Cmv%2Cmvi%2Cpl%2Cinitcwndbps&lsig=AG3C_xAwRAIgB15CJADXFxPPDbJ4XnseUAUVmMag16XzeRvl9GCCqOYCIHM7d8jQhHjJs8-2ze5qDOUa-vJitGWE9Y9cU6mI82MA", "vcodec": "avc1.64001F", "width": 1280, "ext": "mp4", "filesize": null, "fps": 25, "acodec": "mp4a.40.2"}], "playlist_uploader_id": null, "resolution": null, "width": 2560, "n_entries": 835, "age_limit": 0}